monkie/monkie.py
monkie/tests/monkie_test.py
monkie/tests/test_im_5d.tif
monkie-2025.8.6.2.dist-info/licenses/LICENSE
monkie-2025.8.6.2.dist-info/METADATA
monkie-2025.8.6.2.dist-info/WHEEL
monkie-2025.8.6.2.dist-info/top_level.txt
monkie-2025.8.6.2.dist-info/RECORD
