Metadata-Version: 2.4
Name: monkie
Version: 2025.8.6.2
Summary: monkie is a Marimo NotebooK Image Explorer
Author-email: Raymond Hawkins <raymond.hawkins99@gmail.com>, Rodrigo Fernandez-Gonzalez <rodrigo.fernandez.gonzalez@utoronto.ca>
License-Expression: GPL-3.0-or-later
Project-URL: Homepage, https://bitbucket.org/raymond_hawkins_utor/monkie
Project-URL: Bug Tracker, https://bitbucket.org/raymond_hawkins_utor/monkie/issues
Classifier: Programming Language :: Python :: 3.10
Classifier: Programming Language :: Python :: 3.11
Classifier: Programming Language :: Python :: 3.12
Classifier: Operating System :: OS Independent
Requires-Python: >=3.10
License-File: LICENSE
Requires-Dist: marimo
Requires-Dist: numpy>=1.23
Requires-Dist: scikit-image
Requires-Dist: scipy
Dynamic: license-file
